{
  "uuid": "8a9299c8-ec2b-4184-94b3-ff031b290da8",
  "lastMigration": 25,
  "name": "Task api mocks",
  "endpointPrefix": "",
  "latency": 0,
  "port": 3001,
  "hostname": "0.0.0.0",
  "folders": [],
  "routes": [
    {
      "uuid": "09042fcd-80e0-444f-b6aa-391fd1c09d6a",
      "documentation": "",
      "method": "get",
      "endpoint": "tasks/:date",
      "responses": [
        {
          "uuid": "c9a7719c-eaab-491f-b764-3826f4815c89",
          "body": "[\n  {\"title\": \"Task 1\"},\n  {\"title\": \"Task 2\"},\n  {\"title\": \"Task 3\"},\n  {\"title\": \"Task 4\"},\n  {\"title\": \"Task 5\"},\n  {\"title\": \"Task 6\"},\n  {\"title\": \"Task 7\"},\n  {\"title\": \"Task 8\"}\n]",
          "latency": 0,
          "statusCode": 200,
          "label": "",
          "headers": [],
          "bodyType": "INLINE",
          "filePath": "",
          "databucketID": "",
          "sendFileAsBody": false,
          "rules": [],
          "rulesOperator": "OR",
          "disableTemplating": false,
          "fallbackTo404": false,
          "default": true
        }
      ],
      "enabled": true,
      "responseMode": null
    },
    {
      "uuid": "3826a19b-3381-406c-95fb-840b9f27c8e5",
      "documentation": "",
      "method": "post",
      "endpoint": "tasks/:date",
      "responses": [
        {
          "uuid": "9c170079-ac34-411e-8b80-c749a4380c91",
          "body": "{}",
          "latency": 0,
          "statusCode": 200,
          "label": "",
          "headers": [],
          "bodyType": "INLINE",
          "filePath": "",
          "databucketID": "",
          "sendFileAsBody": false,
          "rules": [],
          "rulesOperator": "OR",
          "disableTemplating": false,
          "fallbackTo404": false,
          "default": true
        }
      ],
      "enabled": true,
      "responseMode": null
    },
    {
      "uuid": "f769d960-5db6-49d8-b6fa-d27c69ddf917",
      "documentation": "",
      "method": "delete",
      "endpoint": "tasks/:date/:title",
      "responses": [
        {
          "uuid": "9d697786-d3ab-4f10-865b-f9cb7fccb718",
          "body": "{}",
          "latency": 0,
          "statusCode": 200,
          "label": "",
          "headers": [],
          "bodyType": "INLINE",
          "filePath": "",
          "databucketID": "",
          "sendFileAsBody": false,
          "rules": [],
          "rulesOperator": "OR",
          "disableTemplating": false,
          "fallbackTo404": false,
          "default": true
        }
      ],
      "enabled": true,
      "responseMode": null
    }
  ],
  "rootChildren": [
    {
      "type": "route",
      "uuid": "09042fcd-80e0-444f-b6aa-391fd1c09d6a"
    },
    {
      "type": "route",
      "uuid": "3826a19b-3381-406c-95fb-840b9f27c8e5"
    },
    {
      "type": "route",
      "uuid": "f769d960-5db6-49d8-b6fa-d27c69ddf917"
    }
  ],
  "proxyMode": false,
  "proxyHost": "",
  "proxyRemovePrefix": false,
  "tlsOptions": {
    "enabled": false,
    "type": "CERT",
    "pfxPath": "",
    "certPath": "",
    "keyPath": "",
    "caPath": "",
    "passphrase": ""
  },
  "cors": true,
  "headers": [
    {
      "key": "Content-Type",
      "value": "application/json"
    },
    {
      "key": "Access-Control-Allow-Origin",
      "value": "*"
    },
    {
      "key": "Access-Control-Allow-Methods",
      "value": "GET,POST,PUT,PATCH,DELETE,HEAD,OPTIONS"
    },
    {
      "key": "Access-Control-Allow-Headers",
      "value": "Content-Type, Origin, Accept, Authorization, Content-Length, X-Requested-With"
    }
  ],
  "proxyReqHeaders": [
    {
      "key": "",
      "value": ""
    }
  ],
  "proxyResHeaders": [
    {
      "key": "",
      "value": ""
    }
  ],
  "data": []
}